rubika_bot_api/__init__.py
rubika_bot_api/antispam.py
rubika_bot_api/api.py
rubika_bot_api/config.py
rubika_bot_api/context.py
rubika_bot_api/decorators.py
rubika_bot_api/enums.py
rubika_bot_api/exceptions.py
rubika_bot_api/filters.py
rubika_bot_api/helpers.py
rubika_bot_api/jobs.py
rubika_bot_api/keyboards.py
rubika_bot_api/keypad.py
rubika_bot_api/logger.py
rubika_bot_api/message_queue.py
rubika_bot_api/socket_manager.py
rubika_bot_api/update.py
rubika_bot_api/utils.py
rubika_bot_api/bot/__init__.py
rubika_bot_api/bot/dict_like.py
rubika_bot_api/bot/enums.py
rubika_bot_api/bot/exceptions.py
rubika_bot_api/bot/filters.py
rubika_bot_api/bot/models.py
rubika_bot_api/client_bot/__init__.py
rubika_bot_api/client_bot/enums.py
rubika_bot_api/client_bot/exceptions.py
rubika_bot_api/client_bot/client/__init__.py
rubika_bot_api/client_bot/client/client.py
rubika_bot_api/client_bot/crypto/__init__.py
rubika_bot_api/client_bot/crypto/crypto.py
rubika_bot_api/client_bot/methods/__init__.py
rubika_bot_api/client_bot/methods/methods.py
rubika_bot_api/client_bot/network/__init__.py
rubika_bot_api/client_bot/network/helper.py
rubika_bot_api/client_bot/network/network.py
rubika_bot_api/client_bot/network/socket.py
rubika_bot_api/client_bot/sessions/__init__.py
rubika_bot_api/client_bot/sessions/sessions.py
rubika_bot_api/client_bot/types/__init__.py
rubika_bot_api/client_bot/types/socket/__init__.py
rubika_bot_api/client_bot/types/socket/message.py
rubika_bot_api/client_bot/utils/__init__.py
rubika_bot_api/client_bot/utils/configs.py
rubika_bot_api/client_bot/utils/utils.py
rubika_bot_api/enums/__init__.py
rubika_bot_api/enums/parse_mode.py
rubika_bot_api/parser/__init__.py
rubika_bot_api/parser/markdown.py
rubika_bot_api-1.2.0.dist-info/licenses/LICENCE
rubika_bot_api-1.2.0.dist-info/METADATA
rubika_bot_api-1.2.0.dist-info/WHEEL
rubika_bot_api-1.2.0.dist-info/top_level.txt
rubika_bot_api-1.2.0.dist-info/RECORD
